rqle_ai_langchain_util/__init__.py
rqle_ai_langchain_util/apps/__init__.py
rqle_ai_langchain_util/apps/clarity_genie/README.md
rqle_ai_langchain_util/apps/clarity_genie/__init__.py
rqle_ai_langchain_util/apps/clarity_genie/clarity_genie.py
rqle_ai_langchain_util/apps/clarity_genie/clarity_genie_ui.py
rqle_ai_langchain_util/apps/pod_protocol/README.md
rqle_ai_langchain_util/apps/pod_protocol/__init__.py
rqle_ai_langchain_util/apps/pod_protocol/pod_protocol.py
rqle_ai_langchain_util/apps/techtype_rocket/README.md
rqle_ai_langchain_util/apps/techtype_rocket/__init__.py
rqle_ai_langchain_util/apps/techtype_rocket/techtype_rocket.py
rqle_ai_langchain_util/apps/techtype_rocket/techtype_rocket_ui.py
rqle_ai_langchain_util/llms/__init__.py
rqle_ai_langchain_util/llms/adapters/__init__.py
rqle_ai_langchain_util/llms/adapters/aws_bedrock_adapter.py
rqle_ai_langchain_util/llms/adapters/azure_openai_adapter.py
rqle_ai_langchain_util/llms/adapters/google_gemini_adapter.py
rqle_ai_langchain_util/llms/adapters/llm_adapters.py
rqle_ai_langchain_util/llms/adapters/oci_ai_adapter.py
rqle_ai_langchain_util/llms/adapters/ollama_adapter.py
rqle_ai_langchain_util/llms/llm_guard_validator.py
rqle_ai_langchain_util/llms/llm_mediator.py
rqle_ai_langchain_util/prompts/__init__.py
rqle_ai_langchain_util/prompts/prompt_config.py
rqle_ai_langchain_util/prompts/prompt_example.py
rqle_ai_langchain_util/prompts/prompt_template.py
rqle_ai_langchain_util/settings.py
rqle_ai_langchain_util/utils/__init__.py
rqle_ai_langchain_util/utils/file_util.py
rqle_ai_langchain_util/utils/gui_util.py
rqle_ai_langchain_util/utils/video_util.py
rqle_ai_langchain_util-0.5.0.dist-info/LICENSE
rqle_ai_langchain_util-0.5.0.dist-info/METADATA
rqle_ai_langchain_util-0.5.0.dist-info/WHEEL
rqle_ai_langchain_util-0.5.0.dist-info/RECORD
