Metadata-Version: 2.3
Name: rqle-ai-langchain-util
Version: 0.5.0
Summary: Library facilitating the integration of different LLM providers in LangChain (e.g. `ollama`, `Google Gemini`, etc).
License: Apache-2.0
Keywords: langchain,generative ai,llm
Author: RQle.ai
Requires-Python: >=3.11,<3.12
Classifier: Programming Language :: Python
Requires-Dist: boto3 (>=1.36,<2.0)
Requires-Dist: coverage-badge (>=1,<2)
Requires-Dist: google-generativeai (>=0.8,<0.9)
Requires-Dist: huggingface-hub (>=0.27,<0.28)
Requires-Dist: langchain (>=0.3,<0.4)
Requires-Dist: langchain-aws (>=0.2,<0.3)
Requires-Dist: langchain-community (>=0.3,<0.4)
Requires-Dist: langchain-core (>=0.3,<0.4)
Requires-Dist: langchain-google-genai (>=2,<3)
Requires-Dist: langchain-ollama (>=0.2,<0.3)
Requires-Dist: langchain_openai (>=0.3,<0.4)
Requires-Dist: llm-guard (>=0.3,<0.4)
Requires-Dist: moviepy (>=2,<3)
Requires-Dist: oci (>=2.139,<3.0)
Requires-Dist: plotly (>=5.20,<6.0)
Requires-Dist: pocketsphinx (>=5,<6)
Requires-Dist: pydub (>=0.25,<0.26)
Requires-Dist: python-dotenv (>=1,<2)
Requires-Dist: pytube (>=15,<16)
Requires-Dist: speechrecognition (>=3.10,<4.0)
Requires-Dist: streamlit (>=1.32,<2.0)
Requires-Dist: streamlit-tags (>=1.2,<2.0)
Requires-Dist: traceloop-sdk (>=0.33,<0.34)
Requires-Dist: vosk (>=0.3,<0.4)
Project-URL: Bug Tracker, https://github.com/RQledotai/rqle-ai-langchain-util/issues
Project-URL: Homepage, https://www.linkedin.com/company/102641077
Project-URL: Repository, https://github.com/RQledotai/rqle-ai-langchain-util.git
